<?xml version="1.0" encoding="ISO-8859-1"?>

<SourceList>
    <Source Name="Ge68">
        <FitPars Function="MCShape" CalibHeight="-850">
            <Amp value="2500"></Amp>
            <Mean value="4100"></Mean>
            <Sigma value="2.0"></Sigma>
            <ELeapFrac value="250"></ELeapFrac>
            <MatchMean value="3433.33"></MatchMean>
        </FitPars>
        
        <FitPars Function="MCShape" CalibHeight="-800">
            <Amp value="2500"></Amp>
            <Mean value="4100"></Mean>
            <Sigma value="2.0"></Sigma>
            <ELeapFrac value="250"></ELeapFrac>
            <MatchMean value="3664.39"></MatchMean>
        </FitPars>

        <FitPars Function="MCShape" CalibHeight="-750">
            <Amp value="2500"></Amp>
            <Mean value="4100"></Mean>
            <Sigma value="2.0"></Sigma>
            <ELeapFrac value="250"></ELeapFrac>
            <MatchMean value="3803.09"></MatchMean>
        </FitPars>

        <FitPars Function="MCShape" CalibHeight="-700">
            <Amp value="2500"></Amp>
            <Mean value="4100"></Mean>
            <Sigma value="2.0"></Sigma>
            <ELeapFrac value="250"></ELeapFrac>
            <MatchMean value="3890.4"></MatchMean>
        </FitPars>

        <FitPars Function="MCShape" CalibHeight="-650">
            <Amp value="2500"></Amp>
            <Mean value="4100"></Mean>
            <Sigma value="2.0"></Sigma>
            <ELeapFrac value="250"></ELeapFrac>
            <MatchMean value="3948.36"></MatchMean>
        </FitPars>

        <FitPars Function="MCShape" CalibHeight="-600">
            <Amp value="2500"></Amp>
            <Mean value="4100"></Mean>
            <Sigma value="2.0"></Sigma>
            <ELeapFrac value="250"></ELeapFrac>
            <MatchMean value="3988.0"></MatchMean>
        </FitPars>

        <FitPars Function="MCShape" CalibHeight="-550">
            <Amp value="2500"></Amp>
            <Mean value="4100"></Mean>
            <Sigma value="2.0"></Sigma>
            <ELeapFrac value="250"></ELeapFrac>
            <MatchMean value="4018.19"></MatchMean>
        </FitPars>

        <FitPars Function="MCShape" CalibHeight="-500">
            <Amp value="2500"></Amp>
            <Mean value="4100"></Mean>
            <Sigma value="2.0"></Sigma>
            <ELeapFrac value="250"></ELeapFrac>
            <MatchMean value="4040.71"></MatchMean>
        </FitPars>

        <FitPars Function="MCShape" CalibHeight="-400">
            <Amp value="2500"></Amp>
            <Mean value="4100"></Mean>
            <Sigma value="2.0"></Sigma>
            <ELeapFrac value="250"></ELeapFrac>
            <MatchMean value="4071.82"></MatchMean>
        </FitPars>

        <FitPars Function="MCShape" CalibHeight="-300">
            <Amp value="2500"></Amp>
            <Mean value="4100"></Mean>
            <Sigma value="2.0"></Sigma>
            <ELeapFrac value="250"></ELeapFrac>
            <MatchMean value="4091.34"></MatchMean>
        </FitPars>

        <FitPars Function="MCShape" CalibHeight="-200">
            <Amp value="2500"></Amp>
            <Mean value="4100"></Mean>
            <Sigma value="2.0"></Sigma>
            <ELeapFrac value="250"></ELeapFrac>
            <MatchMean value="4103.22"></MatchMean>
        </FitPars>

        <FitPars Function="MCShape" CalibHeight="-100">
            <Amp value="2500"></Amp>
            <Mean value="4100"></Mean>
            <Sigma value="2.0"></Sigma>
            <ELeapFrac value="250"></ELeapFrac>
            <MatchMean value="4109.85"></MatchMean>
        </FitPars>

        <FitPars Function="MCShape" CalibHeight="0">
            <Amp value="2500"></Amp>
            <Mean value="4100"></Mean>
            <Sigma value="2.0"></Sigma>
            <ELeapFrac value="250"></ELeapFrac>
            <MatchMean value="4111.84"></MatchMean>
        </FitPars>

        <FitPars Function="MCShape" CalibHeight="100">
            <Amp value="2500"></Amp>
            <Mean value="4100"></Mean>
            <Sigma value="2.0"></Sigma>
            <ELeapFrac value="250"></ELeapFrac>
            <MatchMean value="4109.52"></MatchMean>
        </FitPars>

        <FitPars Function="MCShape" CalibHeight="200">
            <Amp value="2500"></Amp>
            <Mean value="4100"></Mean>
            <Sigma value="2.0"></Sigma>
            <ELeapFrac value="250"></ELeapFrac>
            <MatchMean value="4103.37"></MatchMean>
        </FitPars>

        <FitPars Function="MCShape" CalibHeight="300">
            <Amp value="2500"></Amp>
            <Mean value="4100"></Mean>
            <Sigma value="2.0"></Sigma>
            <ELeapFrac value="250"></ELeapFrac>
            <MatchMean value="4091.11"></MatchMean>
        </FitPars>

        <FitPars Function="MCShape" CalibHeight="400">
            <Amp value="2500"></Amp>
            <Mean value="4100"></Mean>
            <Sigma value="2.0"></Sigma>
            <ELeapFrac value="250"></ELeapFrac>
            <MatchMean value="4071.73"></MatchMean>
        </FitPars>

        <FitPars Function="MCShape" CalibHeight="500">
            <Amp value="2500"></Amp>
            <Mean value="4100"></Mean>
            <Sigma value="2.0"></Sigma>
            <ELeapFrac value="250"></ELeapFrac>
            <MatchMean value="4040.47"></MatchMean>
        </FitPars>

        <FitPars Function="MCShape" CalibHeight="550">
            <Amp value="2500"></Amp>
            <Mean value="4100"></Mean>
            <Sigma value="2.0"></Sigma>
            <ELeapFrac value="250"></ELeapFrac>
            <MatchMean value="4018.03"></MatchMean>
        </FitPars>

        <FitPars Function="MCShape" CalibHeight="600">
            <Amp value="2500"></Amp>
            <Mean value="4100"></Mean>
            <Sigma value="2.0"></Sigma>
            <ELeapFrac value="250"></ELeapFrac>
            <MatchMean value="3987.68"></MatchMean>
        </FitPars>

        <FitPars Function="MCShape" CalibHeight="650">
            <Amp value="2500"></Amp>
            <Mean value="4100"></Mean>
            <Sigma value="2.0"></Sigma>
            <ELeapFrac value="250"></ELeapFrac>
            <MatchMean value="3946.87"></MatchMean>
        </FitPars>

        <FitPars Function="MCShape" CalibHeight="700">
            <Amp value="2500"></Amp>
            <Mean value="4100"></Mean>
            <Sigma value="2.0"></Sigma>
            <ELeapFrac value="250"></ELeapFrac>
            <MatchMean value="3889.43"></MatchMean>
        </FitPars>

        <FitPars Function="MCShape" CalibHeight="750">
            <Amp value="2500"></Amp>
            <Mean value="4100"></Mean>
            <Sigma value="2.0"></Sigma>
            <ELeapFrac value="250"></ELeapFrac>
            <MatchMean value="3801.53"></MatchMean>
        </FitPars>

        <FitPars Function="MCShape" CalibHeight="800">
            <Amp value="2500"></Amp>
            <Mean value="4100"></Mean>
            <Sigma value="2.0"></Sigma>
            <ELeapFrac value="250"></ELeapFrac>
            <MatchMean value="3664.56"></MatchMean>
        </FitPars>

        <FitPars Function="MCShape" CalibHeight="850">
            <Amp value="2500"></Amp>
            <Mean value="4100"></Mean>
            <Sigma value="2.0"></Sigma>
            <ELeapFrac value="250"></ELeapFrac>
            <MatchMean value="3431.71"></MatchMean>
        </FitPars>
    </Source>
</SourceList>
